nb_cli_plugin_zhenxun/__init__.py
nb_cli_plugin_zhenxun/cli.py
nb_cli_plugin_zhenxun/commands/__init__.py
nb_cli_plugin_zhenxun/commands/create.py
nb_cli_plugin_zhenxun/commands/run.py
nb_cli_plugin_zhenxun/handlers/__init__.py
nb_cli_plugin_zhenxun/handlers/create.py
nb_cli_plugin_zhenxun/handlers/download.py
nb_cli_plugin_zhenxun/meta.py
nb_cli_plugin_zhenxun/plugin.py
nb_cli_plugin_zhenxun/utils/download_help.py
nb_cli_plugin_zhenxun/utils/git_help.py
nb_cli_plugin_zhenxun/utils/github_utils/__init__.py
nb_cli_plugin_zhenxun/utils/github_utils/const.py
nb_cli_plugin_zhenxun/utils/github_utils/func.py
nb_cli_plugin_zhenxun/utils/github_utils/models.py
nb_cli_plugin_zhenxun/utils/http_utils.py
nb_cli_plugin_zhenxun-0.3.0.dist-info/entry_points.txt
nb_cli_plugin_zhenxun-0.3.0.dist-info/LICENSE
nb_cli_plugin_zhenxun-0.3.0.dist-info/METADATA
nb_cli_plugin_zhenxun-0.3.0.dist-info/WHEEL
nb_cli_plugin_zhenxun-0.3.0.dist-info/RECORD
