Metadata-Version: 2.3
Name: nb-cli-plugin-zhenxun
Version: 0.3.0
Summary: Nonebot Cli plugin for zhenxun
License: AGPL
Keywords: nonebot2,nb-cli
Author: HibiKier
Author-email: 775757368@qq.com
Requires-Python: >=3.10,<4.0
Classifier: License :: Other/Proprietary License
Classifier: Programming Language :: Python :: 3
Classifier: Programming Language :: Python :: 3.10
Classifier: Programming Language :: Python :: 3.11
Classifier: Programming Language :: Python :: 3.12
Classifier: Programming Language :: Python :: 3.13
Requires-Dist: aiocache (>=0.12.3,<0.13.0)
Requires-Dist: nb-cli (>=1.0.2,<2.0.0)
Requires-Dist: py-cpuinfo (>=9.0.0,<10.0.0)
Requires-Dist: rich (>=13.3.1,<14.0.0)
Requires-Dist: strenum (>=0.4.15,<0.5.0)
Project-URL: Homepage, https://github.com/zhenxun-org/nb-cli-plugin-zhenxun
